pepper/__init__.py
pepper/pepper.py
pepper/pepper_train.py
pepper/version.py
pepper/build/PEPPER.cpython-36m-darwin.so
pepper/modules/python/AlignmentSummarizer.py
pepper/modules/python/DataStore.py
pepper/modules/python/DataStorePredict.py
pepper/modules/python/FileManager.py
pepper/modules/python/ImageGenerationUI.py
pepper/modules/python/Options.py
pepper/modules/python/Stitch.py
pepper/modules/python/StitchV2.py
pepper/modules/python/__init__.py
pepper/modules/python/call_consensus.py
pepper/modules/python/download_model.py
pepper/modules/python/make_images.py
pepper/modules/python/perform_stitch.py
pepper/modules/python/polish.py
pepper/modules/python/run_hyperband.py
pepper/modules/python/test_models.py
pepper/modules/python/train_models.py
pepper/modules/python/helper/__init__.py
pepper/modules/python/helper/generate_pileup_from_reads.py
pepper/modules/python/helper/hyperband_result.py
pepper/modules/python/models/ModelHander.py
pepper/modules/python/models/Seq2Seq_atn.py
pepper/modules/python/models/__init__.py
pepper/modules/python/models/dataloader.py
pepper/modules/python/models/dataloader_predict.py
pepper/modules/python/models/hyperband.py
pepper/modules/python/models/predict.py
pepper/modules/python/models/predict_distributed_cpu.py
pepper/modules/python/models/predict_distributed_gpu.py
pepper/modules/python/models/resnet.py
pepper/modules/python/models/simple_model.py
pepper/modules/python/models/test.py
pepper/modules/python/models/train.py
pepper/modules/python/models/train_distributed.py
pepper_hp/pepper_hp.py
pepper_hp/pepper_hp_train.py
pepper_hp/build/PEPPER_HP.cpython-36m-darwin.so
pepper_hp/modules/python/AlignmentSummarizer.py
pepper_hp/modules/python/CallVariant.py
pepper_hp/modules/python/CandidateFinder.py
pepper_hp/modules/python/DataStore.py
pepper_hp/modules/python/DataStorePredict.py
pepper_hp/modules/python/ExcludeContigs.py
pepper_hp/modules/python/FileManager.py
pepper_polish-0.1.5.dist-info/DESCRIPTION.rst
pepper_polish-0.1.5.dist-info/METADATA
pepper_polish-0.1.5.dist-info/RECORD
pepper_polish-0.1.5.dist-info/WHEEL
pepper_polish-0.1.5.dist-info/entry_points.txt
pepper_polish-0.1.5.dist-info/metadata.json
pepper_polish-0.1.5.dist-info/top_level.txt
