Metadata-Version: 2.0
Name: pepper-polish
Version: 0.1.5
Summary: RNN based standalone assembly polisher.
Home-page: https://github.com/kishwarshafin/pepper
Author: Kishwar Shafin
Author-email: kishwar.shafin@gmail.com
License: UNKNOWN
Platform: UNKNOWN
Requires-Python: >=3.5.*
Requires-Dist: cython (>=0.29.12)
Requires-Dist: h5py (==2.10.0)
Requires-Dist: hyperopt (==0.2)
Requires-Dist: intervaltree
Requires-Dist: numpy (==1.16.6)
Requires-Dist: onnx
Requires-Dist: onnxruntime
Requires-Dist: pysam
Requires-Dist: pyyaml
Requires-Dist: torch (==1.4.0)
Requires-Dist: torchnet
Requires-Dist: torchvision (==0.5.0)
Requires-Dist: tqdm (==4.38.0)
Requires-Dist: wget (==3.2)
